{
   "ARCH" : "x86_64",
   "BACKEND" : "qemu",
   "CDMODEL" : "scsi-cd",
   "DESKTOP" : "gnomeos",
   "DISTRI" : "gnomeos",
   "FLAVOR" : "iso",
   "HDDMODEL" : "virtio-blk",
   "HDDSIZEGB" : "10",
   "MACHINE" : "qemu_x86_64",
   "NICMAC" : "52:54:00:12:34:56",
   "NICMODEL" : "virtio-net",
   "NICTYPE" : "user",
   "NICVLAN" : "0",
   "NUMDISKS" : "1",
   "PART_TABLE_TYPE" : "gpt",
   "QEMUCPU" : "host",
   "QEMUCPUS" : "2",
   "QEMUPORT" : "20012",
   "QEMURAM" : "2560",
   "QEMUVGA" : "virtio",
   "TEST" : "gnomeos",
   "TEST_SUITE_NAME" : "gnomeos",
   "UEFI" : "1",
   "UEFI_PFLASH_CODE" : "/usr/share/qemu/ovmf-x86_64-code.bin",
   "UEFI_PFLASH_VARS" : "/usr/share/qemu/ovmf-x86_64-vars.bin",
   "VIRTIO_CONSOLE" : "1",
   "VNC_TYPING_LIMIT" : "5"
}
